pysheller/__init__.py
pysheller/app.py
pysheller-0.1.1.dist-info/WHEEL
pysheller-0.1.1.dist-info/METADATA
pysheller-0.1.1.dist-info/RECORD
