Metadata-Version: 2.1
Name: pysheller
Version: 0.1.1
Summary: Small library to create Python application based on shell scripts.
Home-page: https://github.com/samedamci/guzzy
License: ISC
Keywords: package,shell,shell-script
Author: samedamci
Author-email: samedamci@disroot.org
Requires-Python: >=3.9.2,<4.0.0
Classifier: Development Status :: 5 - Production/Stable
Classifier: Intended Audience :: Developers
Classifier: License :: OSI Approved
Classifier: License :: OSI Approved :: ISC License (ISCL)
Classifier: Programming Language :: Python
Classifier: Programming Language :: Python :: 3
Classifier: Programming Language :: Python :: 3.9
Classifier: Programming Language :: Unix Shell
Classifier: Topic :: Software Development :: Libraries
Classifier: Topic :: Utilities
Project-URL: Repository, https://github.com/samedamci/guzzy
